beet_plugins/__init__.py
beet_plugins/latest_snapshot.py
beet_plugins/nbt_literals.py
beet_plugins/resources/latest_snapshot.json
beet_plugins/root_location.py
beet_plugins/scoreboard.py
beet_plugins/utils/chunk.bolt
beet_plugins/utils/data.bolt
beet_plugins/utils/db.bolt
beet_plugins/utils/dynamic_pos.bolt
beet_plugins/utils/entity.bolt
beet_plugins/utils/functions.bolt
beet_plugins/utils/lantern.bolt
beet_plugins/utils/math.bolt
beet_plugins/utils/objectives.bolt
beet_plugins/utils/path.bolt
beet_plugins/utils/tags.bolt
beet_plugins/utils/uuid.bolt
beet_plugins/utils.py
beet_plugins-0.9.1.dist-info/LICENSE
beet_plugins-0.9.1.dist-info/METADATA
beet_plugins-0.9.1.dist-info/WHEEL
beet_plugins-0.9.1.dist-info/RECORD
