Metadata-Version: 2.1
Name: beet-plugins
Version: 0.9.1
Summary: 
Author: TheWii
Author-email: 67249660+TheWii@users.noreply.github.com
Requires-Python: >=3.10,<4.0
Classifier: Programming Language :: Python :: 3
Classifier: Programming Language :: Python :: 3.10
Classifier: Programming Language :: Python :: 3.11
Requires-Dist: bolt (>=0.37.0)
Requires-Dist: bolt-expressions (>=0.12.2)
Requires-Dist: mecha (>=0.74.0)
Requires-Dist: packaging (>=23.1,<24.0)
